dmiparser/__init__.py
dmiparser/__main__.py
dmiparser/dmiparser.py
dmiparser/dmidecoder/__init__.py
dmiparser/dmidecoder/__main__.py
dmiparser/dmidecoder/dmidecoder.py
tests/__init__.py
tests/test_dmidecode_10.py
tests/test_dmidecode_13.py
tests/test_dmidecode_148.py
tests/test_dmidecode_32.py
tests/test_dmidecode_9.py
tests/test_dmidecode_full.py
dmiparser-5.0.dist-info/LICENSE
dmiparser-5.0.dist-info/METADATA
dmiparser-5.0.dist-info/WHEEL
dmiparser-5.0.dist-info/entry_points.txt
dmiparser-5.0.dist-info/top_level.txt
dmiparser-5.0.dist-info/zip-safe
dmiparser-5.0.dist-info/RECORD
