Metadata-Version: 2.1
Name: dmiparser
Version: 5.0
Summary: This parse dmidecode output to JSON text
Home-page: https://github.com/Arondight/python-dmiparser
Download-URL: https://github.com/Arondight/python-dmiparser/tags
Author: Qin Fandong
Author-email: shell_way@foxmail.com
License: MIT License
Platform: Any
Classifier: License :: OSI Approved :: MIT License
Classifier: Operating System :: OS Independent
Classifier: Programming Language :: Python
Classifier: Programming Language :: Python :: 3
Classifier: Programming Language :: Python :: 3 :: Only
Classifier: Programming Language :: Python :: 3.10
Classifier: Programming Language :: Python :: 3.6
Classifier: Programming Language :: Python :: 3.7
Classifier: Programming Language :: Python :: 3.8
Classifier: Programming Language :: Python :: 3.9
License-File: LICENSE
